ambient_bd_downloader/__init__.py
ambient_bd_downloader/generate_config.py
ambient_bd_downloader/main.py
ambient_bd_downloader/download/__init__.py
ambient_bd_downloader/download/compliance.py
ambient_bd_downloader/download/data_download.py
ambient_bd_downloader/properties/__init__.py
ambient_bd_downloader/properties/properties.py
ambient_bd_downloader/sf_api/__init__.py
ambient_bd_downloader/sf_api/dom.py
ambient_bd_downloader/sf_api/somnofy.py
ambient_bd_downloader/storage/__init__.py
ambient_bd_downloader/storage/paths_resolver.py
ambient_bd_downloader-0.6.0.dist-info/licenses/LICENSE
ambient_bd_downloader-0.6.0.dist-info/METADATA
ambient_bd_downloader-0.6.0.dist-info/WHEEL
ambient_bd_downloader-0.6.0.dist-info/entry_points.txt
ambient_bd_downloader-0.6.0.dist-info/top_level.txt
ambient_bd_downloader-0.6.0.dist-info/RECORD
