Metadata-Version: 2.4
Name: ambient_bd_downloader
Version: 0.6.0
Summary: Download data from Somnofy devices
Home-page: https://github.com/chronopsychiatry/AMBIENT-BD-Somnofy-Data-Download
Requires-Python: >=3.10
License-File: LICENSE
Requires-Dist: pandas>=1.5.3
Requires-Dist: requests>=2.31.0
Requires-Dist: requests-oauthlib>=2.0.0
Dynamic: description-content-type
Dynamic: home-page
Dynamic: license-file
Dynamic: requires-dist
Dynamic: requires-python
Dynamic: summary
